klax/__init__.py
klax/_callbacks.py
klax/_datahandler.py
klax/_losses.py
klax/_misc.py
klax/_serialization.py
klax/_training.py
klax/_wrappers.py
klax/py.typed
klax/nn/__init__.py
klax/nn/_icnn.py
klax/nn/_linear.py
klax/nn/_matrices.py
klax/nn/_mlp.py
klax-0.1.3.dist-info/METADATA
klax-0.1.3.dist-info/WHEEL
klax-0.1.3.dist-info/licenses/LICENSE
klax-0.1.3.dist-info/licenses/NOTICE
klax-0.1.3.dist-info/RECORD
