Metadata-Version: 2.4
Name: klax
Version: 0.1.3
Summary: A lightweight machine learning package for computational mechanics.
Project-URL: Repository, https://github.com/Drenderer/klax
Project-URL: Issues, https://github.com/Drenderer/klax/issues
Author-email: Fabian Roth <roth@cps.tu-darmstadt.de>, Jasper Schommartz <schommartz@cps.tu-darmstadt.de>
License:                                  Apache License
License-File: LICENSE
License-File: NOTICE
Classifier: Development Status :: 3 - Alpha
Classifier: Intended Audience :: Education
Classifier: Intended Audience :: Science/Research
Classifier: License :: OSI Approved :: Apache Software License
Classifier: Natural Language :: English
Classifier: Operating System :: OS Independent
Classifier: Programming Language :: Python :: 3
Classifier: Topic :: Scientific/Engineering :: Artificial Intelligence
Classifier: Topic :: Scientific/Engineering :: Mathematics
Classifier: Topic :: Scientific/Engineering :: Physics
Requires-Python: >=3.12
Requires-Dist: equinox>=0.12.2
Requires-Dist: jax>=0.6.0
Requires-Dist: optax>=0.2.4
Requires-Dist: paramax>=0.0.3
Provides-Extra: docs
Requires-Dist: hippogriffe>=0.2.2; extra == 'docs'
Requires-Dist: mkdocs-ipynb>=0.1.1; extra == 'docs'
Requires-Dist: mkdocs-material>=9.6.14; extra == 'docs'
Requires-Dist: mkdocs>=1.6.1; extra == 'docs'
Requires-Dist: mkdocstrings-python>=1.16.12; extra == 'docs'
Provides-Extra: plot
Requires-Dist: matplotlib>=3.10.3; extra == 'plot'
